DNAcore/__init__.py
DNAcore/dnalib.py
helper/__init__.py
helper/helper.py
obreva/ADEN.py
obreva/__init__.py
obreva/l_system.py
obreva/mandelbrot.py
obreva/sever.py
obreva-0.0.9.dist-info/METADATA
obreva-0.0.9.dist-info/WHEEL
obreva-0.0.9.dist-info/licenses/LICENSE
obreva-0.0.9.dist-info/RECORD
